tinyDisplay/__init__.py
tinyDisplay/cfg.py
tinyDisplay/exceptions.py
tinyDisplay/font.py
tinyDisplay/globalVars.py
tinyDisplay/render/__init__.py
tinyDisplay/render/collection.py
tinyDisplay/render/fonts/hd44780.fnt
tinyDisplay/render/fonts/hd44780a00.png
tinyDisplay/render/fonts/hd44780a02.png
tinyDisplay/render/profileWidget.py
tinyDisplay/render/widget.py
tinyDisplay/utility.py
tinydisplay-0.1.3.dist-info/METADATA
tinydisplay-0.1.3.dist-info/WHEEL
tinydisplay-0.1.3.dist-info/RECORD
