Metadata-Version: 2.1
Name: tinyDisplay
Version: 0.1.3
Summary: A widget library and window manager for small displays
Home-page: https://github.com/dhrone/tinyDisplay
License: MIT
Keywords: tinyDisplay,luma.oled,luma.lcd,display,hd44780,ssd1306,winstar
Author: dhrone
Author-email: dhrone@dhrone.xyz
Requires-Python: >=3.9,<4.0
Classifier: Development Status :: 3 - Alpha
Classifier: Environment :: Console
Classifier: Intended Audience :: Developers
Classifier: License :: OSI Approved :: MIT License
Classifier: Operating System :: OS Independent
Classifier: Programming Language :: Python :: 3
Classifier: Programming Language :: Python :: 3.9
Classifier: Programming Language :: Python :: 3.10
Classifier: Programming Language :: Python :: 3.11
Classifier: Programming Language :: Python :: 3.12
Classifier: Topic :: Software Development :: Libraries :: Python Modules
Requires-Dist: pillow (>=10.3.0,<11.0.0)
Requires-Dist: pyyaml (>=6.0.1,<7.0.0)
Requires-Dist: requests (>=2.25.1,<3.0.0)
Requires-Dist: simple-pid (>=0.2.4,<0.3.0)
Project-URL: Repository, https://github.com/dhrone/tinydDisplay
